picat_kernel/__init__.py
picat_kernel/__main__.py
picat_kernel/kernel.py
picat_kernel-0.1.data/data/share/jupyter/kernels/picat/kernel.json
picat_kernel-0.1.dist-info/LICENSE.txt
picat_kernel-0.1.dist-info/METADATA
picat_kernel-0.1.dist-info/WHEEL
picat_kernel-0.1.dist-info/top_level.txt
picat_kernel-0.1.dist-info/RECORD
