Metadata-Version: 2.1
Name: picat-kernel
Version: 0.1
Summary: A Picat kernel for Jupyter
Home-page: https://gitlab.com/minicz/picat_kernel
Maintainer: Marcio Minicz
Maintainer-email: marciominicz@gmail.com
License: MPL-2.0
Download-URL: https://gitlab.com/minicz/picat_kernel
Platform: Any
Classifier: Intended Audience :: Science/Research
Classifier: License :: OSI Approved :: Mozilla Public License 2.0 (MPL 2.0)
Classifier: Operating System :: MacOS
Classifier: Operating System :: POSIX :: Linux
Classifier: Programming Language :: Python :: 3.5
Classifier: Programming Language :: Python :: 3.6
Classifier: Programming Language :: Python :: 3.7
Classifier: Topic :: Scientific/Engineering
Classifier: Topic :: Software Development
Classifier: Topic :: System :: Shells
Classifier: Framework :: Jupyter
Requires: metakernel
Requires: jupyter
Requires-Dist: metakernel
Requires-Dist: jupyter
